stsoidcdriver.py
sts_oidc_driver-1.0.1.dist-info/licenses/LICENSE
sts_oidc_driver-1.0.1.dist-info/licenses/NOTICE
sts_oidc_driver-1.0.1.dist-info/METADATA
sts_oidc_driver-1.0.1.dist-info/WHEEL
sts_oidc_driver-1.0.1.dist-info/entry_points.txt
sts_oidc_driver-1.0.1.dist-info/top_level.txt
sts_oidc_driver-1.0.1.dist-info/RECORD
